bhasa/__init__.py
bhasa/models/__init__.py
bhasa/models/config_mamba.py
bhasa/models/mixer_seq_simple.py
bhasa/modules/__init__.py
bhasa/modules/mamba_simple.py
bhasa/ops/__init__.py
bhasa/ops/causal_conv.py
bhasa/ops/layernorm.py
bhasa/ops/selective_scan_interface.py
bhasa/ops/triton/__init__.py
bhasa/ops/triton/layernorm.py
bhasa/ops/triton/selective_state_update.py
bhasa/utils/__init__.py
bhasa/utils/generation.py
bhasa/utils/hf.py
bhasa-0.1.2.dist-info/AUTHORS
bhasa-0.1.2.dist-info/LICENSE
bhasa-0.1.2.dist-info/METADATA
bhasa-0.1.2.dist-info/WHEEL
bhasa-0.1.2.dist-info/top_level.txt
bhasa-0.1.2.dist-info/RECORD
