Metadata-Version: 2.1
Name: bhasa
Version: 0.1.2
Summary: Mamba state-space model
Home-page: https://github.com/state-spaces/mamba
Author: Tri Dao, Albert Gu
Author-email: tri@tridao.me, agu@cs.cmu.edu
Classifier: Programming Language :: Python :: 3
Classifier: License :: OSI Approved :: BSD License
Classifier: Operating System :: Unix
Requires-Python: >=3.7
License-File: LICENSE
License-File: AUTHORS
Requires-Dist: torch
Requires-Dist: packaging
Requires-Dist: ninja
Requires-Dist: einops
Requires-Dist: transformers
